fastapi_generator/__init__.py
fastapi_generator/cli.py
fastapi_generator/commands/__init__.py
fastapi_generator/commands/config.py
fastapi_generator/commands/new.py
fastapi_generator/core/__init__.py
fastapi_generator/core/config.py
fastapi_generator/core/post_deployment_setup.py
fastapi_generator/core/templates.py
fastapi_generator/core/utils.py
fastapi_generator/templates/async/async_db.py.jinja
fastapi_generator/templates/base/.env.jinja
fastapi_generator/templates/base/.gitignore.jinja
fastapi_generator/templates/base/__init__.py.jinja
fastapi_generator/templates/base/api_v1__init__.py.jinja
fastapi_generator/templates/base/auth.py.jinja
fastapi_generator/templates/base/config.py.jinja
fastapi_generator/templates/base/database.py.jinja
fastapi_generator/templates/base/loguru.py.jinja
fastapi_generator/templates/base/main.py.jinja
fastapi_generator/templates/base/models.py.jinja
fastapi_generator/templates/base/pyproject.toml.jinja
fastapi_generator/templates/base/README.md.jinja
fastapi_generator/templates/base/schemas.py.jinja
fastapi_generator/templates/base/security.py.jinja
fastapi_generator/templates/celery/celery_app.py.jinja
fastapi_generator/templates/celery/config.py.jinja
fastapi_generator/templates/celery/email_base.py.jinja
fastapi_generator/templates/celery/tasks.py.jinja
fastapi_generator/templates/docker/docker-compose.yml.jinja
fastapi_generator/templates/docker/fastapi/celery/async/beat/start.sh.jinja
fastapi_generator/templates/docker/fastapi/celery/async/flower/start.sh.jinja
fastapi_generator/templates/docker/fastapi/celery/async/worker/start.sh.jinja
fastapi_generator/templates/docker/fastapi/celery/sync/beat/start.sh.jinja
fastapi_generator/templates/docker/fastapi/celery/sync/flower/start.sh.jinja
fastapi_generator/templates/docker/fastapi/celery/sync/worker/start.sh.jinja
fastapi_generator/templates/docker/fastapi/Dockerfile
fastapi_generator/templates/docker/fastapi/entrypoint.sh.jinja
fastapi_project_starter-1.2.0.dist-info/entry_points.txt
fastapi_project_starter-1.2.0.dist-info/LICENSE
fastapi_project_starter-1.2.0.dist-info/METADATA
fastapi_project_starter-1.2.0.dist-info/WHEEL
fastapi_project_starter-1.2.0.dist-info/RECORD
