Metadata-Version: 2.3
Name: fastapi-project-starter
Version: 1.2.0
Summary:  Fastgen - FastAPI Project Generator & Scaffolder. Create production-ready FastAPI projects with modern features.
Keywords: fastapi,template,generator,scaffold,boilerplate,typer,cli,python
Author: Devesh Shrestha
Author-email: deveshshrestha20@gmail.com
Requires-Python: >=3.8,<4.0
Classifier: Development Status :: 4 - Beta
Classifier: Environment :: Console
Classifier: Framework :: FastAPI
Classifier: Intended Audience :: Developers
Classifier: License :: OSI Approved :: MIT License
Classifier: Operating System :: OS Independent
Classifier: Programming Language :: Python :: 3
Classifier: Programming Language :: Python :: 3.8
Classifier: Programming Language :: Python :: 3.9
Classifier: Programming Language :: Python :: 3.10
Classifier: Programming Language :: Python :: 3.11
Classifier: Programming Language :: Python :: 3.12
Classifier: Programming Language :: Python :: 3.13
Classifier: Topic :: Internet :: WWW/HTTP :: HTTP Servers
Classifier: Topic :: Software Development :: Code Generators
Classifier: Topic :: Software Development :: Libraries :: Application Frameworks
Classifier: Topic :: Software Development :: Libraries :: Python Modules
Requires-Dist: jinja2
Requires-Dist: pydantic
Requires-Dist: pydantic-settings
Requires-Dist: rich
Requires-Dist: typer[all]
Project-URL: Documentation, https://github.com/deveshshrestha20/FastAPI_Project_Starter#readme
Project-URL: Homepage, https://github.com/deveshshrestha20/FastAPI_Project_Starter
Project-URL: Repository, https://github.com/deveshshrestha20/FastAPI_Project_Starter
